nrt/data/__init__.py
nrt/data/mreCritValTable.json
nrt/data/simulate.py
nrt_data-0.0.1.post2.dist-info/LICENSE
nrt_data-0.0.1.post2.dist-info/METADATA
nrt_data-0.0.1.post2.dist-info/WHEEL
nrt_data-0.0.1.post2.dist-info/top_level.txt
nrt_data-0.0.1.post2.dist-info/RECORD
