Metadata-Version: 2.1
Name: nrt-data
Version: 0.0.1.post2
Summary: nrt namespace package giving access to demo and test datasets, extracted from nrt core
Author: Jonas Viehweger, Kenji Ose
Author-email: Loic Dutrieux <loic.dutrieux@ec.europa.eu>
Maintainer-email: Loic Dutrieux <loic.dutrieux@ec.europa.eu>
License: EUPL-1.2
Project-URL: homepage, https://code.europa.eu/jrc-forest/nrt-data
Keywords: sentinel2,xarray,zarr,netcdf
Classifier: Programming Language :: Python :: 3
Classifier: Programming Language :: Python :: 3.9
Classifier: Programming Language :: Python :: 3.10
Classifier: Programming Language :: Python :: 3.11
Classifier: License :: OSI Approved :: European Union Public Licence 1.2 (EUPL 1.2)
Requires-Python: >=3.9
License-File: LICENSE
Requires-Dist: numpy
Requires-Dist: xarray
Requires-Dist: rasterio
Requires-Dist: fiona
Requires-Dist: netCDF4
Requires-Dist: zarr
Requires-Dist: aiohttp
Requires-Dist: fsspec
Requires-Dist: pooch
Provides-Extra: docs
Requires-Dist: sphinx; extra == "docs"
Requires-Dist: sphinx-rtd-theme; extra == "docs"
